queued_client_py/__init__.py
queued_client_py-0.1.3.dist-info/METADATA
queued_client_py-0.1.3.dist-info/WHEEL
queued_client_py-0.1.3.dist-info/RECORD
